arthub_api/__init__.py
arthub_api/__main__.py
arthub_api/__version__.py
arthub_api/_internal_utils.py
arthub_api/arthub_api_config.py
arthub_api/asset_matrix.py
arthub_api/blade_api.py
arthub_api/blade_api_instance.py
arthub_api/blade_storage.py
arthub_api/cli.py
arthub_api/config.py
arthub_api/exception.py
arthub_api/models.py
arthub_api/open_api.py
arthub_api/storage.py
arthub_api/utils.py
arthub_api-1.10.8.dist-info/LICENSE
arthub_api-1.10.8.dist-info/METADATA
arthub_api-1.10.8.dist-info/WHEEL
arthub_api-1.10.8.dist-info/entry_points.txt
arthub_api-1.10.8.dist-info/top_level.txt
arthub_api-1.10.8.dist-info/RECORD
