Metadata-Version: 2.1
Name: arthub-api
Version: 1.10.8
Summary: ArHhub Python SDK
Home-page: UNKNOWN
Author: Joey Ding
Author-email: joeyding@tencent.com
License: Apache 2.0
Platform: UNKNOWN
Classifier: Development Status :: 5 - Production/Stable
Classifier: Environment :: Web Environment
Classifier: Intended Audience :: Developers
Classifier: Natural Language :: English
Classifier: Operating System :: OS Independent
Requires-Dist: requests (>=2.25.1)
Requires-Dist: platformdirs (==2.0.2)
Requires-Dist: six (==1.16.*)
Requires-Dist: pycryptodome (==3.16.0)
Requires-Dist: tenacity (==5.0.*) ; python_version < "3"
Requires-Dist: futures ; python_version == "2.7"
Requires-Dist: tenacity (>=8) ; python_version >= "3"
